Metadata-Version: 2.1
Name: elit-morph-analyzer
Version: 1.0
Summary: English Morphological Analyzer from ELIT
Home-page: https://github.com/emorynlp/elit-morph_analyzer
Author: Jinho D. Choi
Author-email: jinho.choi@emory.edu
License: UNKNOWN
Platform: UNKNOWN
Classifier: Programming Language :: Python :: 3
Classifier: License :: OSI Approved :: Apache Software License
Classifier: Operating System :: OS Independent
License-File: LICENSE
